fastapi_and_logging/__init__.py
fastapi_and_logging/enums.py
fastapi_and_logging/helpers.py
fastapi_and_logging/http_clients/__init__.py
fastapi_and_logging/http_clients/httpx.py
fastapi_and_logging/incoming.py
fastapi_and_logging/logging.py
fastapi_and_logging/logging_route.py
fastapi_and_logging-0.0.21.dist-info/LICENSE
fastapi_and_logging-0.0.21.dist-info/METADATA
fastapi_and_logging-0.0.21.dist-info/WHEEL
fastapi_and_logging-0.0.21.dist-info/RECORD
