Metadata-Version: 2.1
Name: fastapi-and-logging
Version: 0.0.21
Summary: FastAPI-and-Logging simplifies log handling, allowing for effective organization, tracking, and analysis of logs in FastAPI applications, aiding in debugging and issue resolut
Home-page: https://github.com/heysaeid/fastapi-and-logging
License: MIT
Keywords: fastapi,fastapi logging,fastapi and logging
Author: Saeid Noormohammadi
Author-email: heysaeid92@gmail.com
Requires-Python: >=3.7,<4.0
Classifier: License :: OSI Approved :: MIT License
Classifier: Programming Language :: Python :: 3
Classifier: Programming Language :: Python :: 3.7
Classifier: Programming Language :: Python :: 3.8
Classifier: Programming Language :: Python :: 3.9
Classifier: Programming Language :: Python :: 3.10
Classifier: Programming Language :: Python :: 3.11
Classifier: Programming Language :: Python :: 3.12
Requires-Dist: fastapi (>=0.104.1,<0.105.0)
Requires-Dist: loguru (>=0.7.2,<0.8.0)
Requires-Dist: user-agents (>=2.2.0,<3.0.0)
Project-URL: Documentation, https://github.com/heysaeid/fastapi-and-logging
Project-URL: Repository, https://github.com/heysaeid/fastapi-and-logging
